letsformat/__init__.py
letsformat/main.py
letsformat/controllers/__init__.py
letsformat/controllers/base.py
letsformat/controllers/convert.py
letsformat/core/__init__.py
letsformat/core/exc.py
letsformat/core/version.py
letsformat/ext/__init__.py
letsformat/plugins/__init__.py
letsformat/templates/__init__.py
letsformat/templates/command1.jinja2
letsformat-0.0.1.dev20201017143053.dist-info/LICENSE.md
letsformat-0.0.1.dev20201017143053.dist-info/METADATA
letsformat-0.0.1.dev20201017143053.dist-info/WHEEL
letsformat-0.0.1.dev20201017143053.dist-info/entry_points.txt
letsformat-0.0.1.dev20201017143053.dist-info/top_level.txt
letsformat-0.0.1.dev20201017143053.dist-info/RECORD
