Metadata-Version: 2.1
Name: letsformat
Version: 0.0.1.dev20201017143053
Summary: Simple File Format Converter
Home-page: https://github.com/matthewholden01/letsformat
Author: Matthew Holden
Author-email: matthewholden01@gmail.com
License: unlicensed
Platform: UNKNOWN
